{
  "vorgangId": "11142",
  "VORGANG": {
    "WAHLPERIODE": "16",
    "VORGANGSTYP": "Schriftliche Frage",
    "TITEL": "Anzahl der F채lle mit der Berechnung des Arbeitslosengeldes nach einer l채nger als 150 Tage dauernden Elternzeit auf der Basis eines Pauschbetrags anstatt des bisherigen Entgelts sowie Anzahl der bisher anh채ngigen Klagen",
    "AKTUELLER_STAND": "Beantwortet",
    "SIGNATUR": "",
    "GESTA_ORDNUNGSNUMMER": "",
    "WICHTIGE_DRUCKSACHE": {
      "DRS_HERAUSGEBER": "BT",
      "DRS_NUMMER": "16/7216",
      "DRS_TYP": "Schriftliche Fragen",
      "DRS_LINK": "http://dipbt.bundestag.de:80/dip21/btd/16/072/1607216.pdf"
    },
    "EU_DOK_NR": "",
    "SCHLAGWORT": [
      {
        "_fundstelle": "true",
        "__cdata": "Arbeitslosengeld"
      },
      {
        "_fundstelle": "true",
        "__cdata": "Elternzeit"
      }
    ],
    "ABSTRAKT": ""
  },
  "VORGANGSABLAUF": {
    "VORGANGSPOSITION": {
      "ZUORDNUNG": "BT",
      "URHEBER": "Schriftliche Frage/Schriftliche Antwort ",
      "FUNDSTELLE": "16.11.2007 - BT-Drucksache 16/7216, Nr. 5",
      "FUNDSTELLE_LINK": "http://dipbt.bundestag.de:80/dip21/btd/16/072/1607216.pdf",
      "PERSOENLICHER_URHEBER": [
        {
          "VORNAME": "Gerd",
          "NACHNAME": "Andres",
          "FUNKTION": "Parl. Staatssekr.",
          "RESSORT": "Bundesministerium f체r Arbeit und Soziales",
          "AKTIVITAETSART": "Antwort"
        },
        {
          "VORNAME": "Ina",
          "NACHNAME": "Lenke",
          "FUNKTION": "MdB",
          "FRAKTION": "FDP",
          "AKTIVITAETSART": "Frage"
        }
      ]
    }
  }
}
