{
  "vorgangId": "276920",
  "VORGANG": {
    "WAHLPERIODE": "19",
    "VORGANGSTYP": "Antrag",
    "TITEL": "Familien entlasten - Einführung eines zinsfreien Kinderkredits",
    "INITIATIVE": "Fraktion der AfD",
    "AKTUELLER_STAND": "Noch nicht beraten",
    "SIGNATUR": "",
    "GESTA_ORDNUNGSNUMMER": "",
    "WICHTIGE_DRUCKSACHE": {
      "DRS_HERAUSGEBER": "BT",
      "DRS_NUMMER": "19/28795",
      "DRS_TYP": "Antrag",
      "DRS_LINK": "http://dipbt.bundestag.de:80/dip21/btd/19/287/1928795.pdf"
    },
    "EU_DOK_NR": "",
    "SACHGEBIET": [
      "Wirtschaft",
      "Gesellschaftspolitik, soziale Gruppen"
    ],
    "SCHLAGWORT": [
      "Eltern",
      {
        "_fundstelle": "true",
        "__cdata": "Familie"
      },
      "KfW-Bankengruppe",
      "Kind",
      {
        "_fundstelle": "true",
        "__cdata": "Kredit"
      }
    ],
    "ABSTRAKT": ""
  },
  "VORGANGSABLAUF": {
    "VORGANGSPOSITION": {
      "ZUORDNUNG": "BT",
      "URHEBER": "Antrag,  Urheber : Fraktion der AfD ",
      "FUNDSTELLE": "21.04.2021 - BT-Drucksache 19/28795",
      "FUNDSTELLE_LINK": "http://dipbt.bundestag.de:80/dip21/btd/19/287/1928795.pdf",
      "PERSOENLICHER_URHEBER": [
        {
          "VORNAME": "Johannes",
          "NACHNAME": "Huber",
          "FUNKTION": "MdB",
          "FRAKTION": "AfD",
          "AKTIVITAETSART": "Antrag"
        },
        {
          "VORNAME": "Marc",
          "NACHNAME": "Bernhard",
          "FUNKTION": "MdB",
          "FRAKTION": "AfD",
          "AKTIVITAETSART": "Antrag"
        }
      ]
    }
  }
}
