{
  "vorgangId": "254213",
  "VORGANG": {
    "WAHLPERIODE": "19",
    "VORGANGSTYP": "Antrag",
    "TITEL": "Für einen Hochschulsozialpakt - 50.000 neue Wohnheimplätze für Studierende",
    "INITIATIVE": "Fraktion DIE LINKE",
    "AKTUELLER_STAND": "Beschlussempfehlung liegt vor",
    "SIGNATUR": "",
    "GESTA_ORDNUNGSNUMMER": "",
    "WICHTIGE_DRUCKSACHE": [
      {
        "DRS_HERAUSGEBER": "BT",
        "DRS_NUMMER": "19/14154",
        "DRS_TYP": "Antrag",
        "DRS_LINK": "http://dipbt.bundestag.de:80/dip21/btd/19/141/1914154.pdf"
      },
      {
        "DRS_HERAUSGEBER": "BT",
        "DRS_NUMMER": "19/24804",
        "DRS_TYP": "Beschlussempfehlung und Bericht",
        "DRS_LINK": "http://dipbt.bundestag.de:80/dip21/btd/19/248/1924804.pdf"
      }
    ],
    "PLENUM": {
      "PLPR_KLARTEXT": "Beratung",
      "PLPR_HERAUSGEBER": "BT",
      "PLPR_NUMMER": "19/121",
      "PLPR_SEITEN": "15034C - 15044C",
      "PLPR_LINK": "http://dipbt.bundestag.de:80/dip21/btp/19/19121.pdf#P.15034"
    },
    "EU_DOK_NR": "",
    "SACHGEBIET": [
      "Bildung und Erziehung",
      "Raumordnung, Bau- und Wohnungswesen"
    ],
    "SCHLAGWORT": [
      "Baufinanzierung",
      "Bundesmittel",
      "Neubau",
      "Öffentliches Bauvorhaben",
      {
        "_fundstelle": "true",
        "__cdata": "Student"
      },
      "Studentenwohnheim",
      {
        "_fundstelle": "true",
        "__cdata": "Wohnheim"
      },
      "Wohnungsbau"
    ],
    "ABSTRAKT": ""
  }
}
