{
  "vorgangId": "114111",
  "VORGANG": {
    "WAHLPERIODE": "14",
    "VORGANGSTYP": "Fragestunde",
    "TITEL": "Ungleichbehandlung der Opfer der Enteignungen zwischen Mai 1945 und Oktober 1949 in der sowjetischen Besatzungszone und denen ab November 1949 (G-SIG: 14054015)",
    "AKTUELLER_STAND": "Beantwortet",
    "SIGNATUR": "",
    "GESTA_ORDNUNGSNUMMER": "",
    "WICHTIGE_DRUCKSACHE": {
      "DRS_HERAUSGEBER": "BT",
      "DRS_NUMMER": "14/8425",
      "DRS_TYP": "Schriftliche Fragen",
      "DRS_LINK": "http://dipbt.bundestag.de:80/dip21/btd/14/084/1408425.pdf"
    },
    "EU_DOK_NR": "",
    "SCHLAGWORT": [
      "Enteignung",
      "Rückerstattung",
      "Sowjetische Besatzungszone"
    ],
    "ABSTRAKT": ""
  },
  "VORGANGSABLAUF": {
    "VORGANGSPOSITION": {
      "ZUORDNUNG": "BT",
      "URHEBER": "Schriftliche Frage/Schriftliche Antwort ",
      "FUNDSTELLE": "01.03.2002 - BT-Drucksache 14/8425, Nr. 3, 4",
      "FUNDSTELLE_LINK": "http://dipbt.bundestag.de:80/dip21/btd/14/084/1408425.pdf",
      "PERSOENLICHER_URHEBER": [
        {
          "PERSON_TITEL": "Dr.",
          "VORNAME": "Eckhart",
          "NACHNAME": "Pick",
          "FUNKTION": "Parl. Staatssekr.",
          "RESSORT": "Bundesministerium der Justiz",
          "AKTIVITAETSART": "Antwort"
        },
        {
          "VORNAME": "Walter",
          "NACHNAME": "Hirche",
          "FUNKTION": "MdB",
          "FRAKTION": "FDP",
          "AKTIVITAETSART": "Frage"
        }
      ]
    }
  }
}
