{
  "vorgangId": "235085",
  "VORGANG": {
    "WAHLPERIODE": "19",
    "VORGANGSTYP": "Kleine Anfrage",
    "TITEL": "Neuorganisation der Financial Intelligence Unit und Zusammenarbeit mit den\r\nStrafverfolgungsbehörden im Bereich der Geldwäsche",
    "INITIATIVE": "Fraktion BÜNDNIS 90/DIE GRÜNEN",
    "AKTUELLER_STAND": "Beantwortet",
    "SIGNATUR": "",
    "GESTA_ORDNUNGSNUMMER": "",
    "WICHTIGE_DRUCKSACHE": [
      {
        "DRS_HERAUSGEBER": "BT",
        "DRS_NUMMER": "19/1959",
        "DRS_TYP": "Kleine Anfrage",
        "DRS_LINK": "http://dipbt.bundestag.de:80/dip21/btd/19/019/1901959.pdf"
      },
      {
        "DRS_HERAUSGEBER": "BT",
        "DRS_NUMMER": "19/2263",
        "DRS_TYP": "Antwort",
        "DRS_LINK": "http://dipbt.bundestag.de:80/dip21/btd/19/022/1902263.pdf"
      }
    ],
    "EU_DOK_NR": "",
    "SACHGEBIET": [
      "Wirtschaft",
      "Recht"
    ],
    "SCHLAGWORT": [
      "Datenaustausch",
      "Datenschutz",
      "Datenspeicherung",
      "Financial Intelligence Unit Deutschland",
      "Geldwäsche",
      "Geldwäschegesetz",
      "Grenzüberschreitende Zusammenarbeit",
      "Internationale Zusammenarbeit",
      "Justizverwaltung",
      "Polizeibehörde",
      "Strafverfolgung",
      "Zollverwaltung"
    ],
    "ABSTRAKT": "Schaffung und Besetzung von Planstellen nach der Verlagerung der Behörde vom BKA zum Zoll, Fallbearbeitungen, Gründe für unbearbeitete Fälle und Rückstau, eilbedürftige Fälle, Verfolgung des strafrechtlichen Verlaufs der weitergegebenen Verdachtsmeldungen, Sicherheitstest der Übermittlungssoftware GoAML, Konsequenzen und Risiken, Umsetzung von Auskunfts- und Datenabrufsrechten, Filterung werthaltiger Fälle, Einhaltung datenschutzrechtlicher Vorgaben, Bedenken betr. möglicher Vorratsdatenspeicherung, Zusammenarbeit zwischen Zoll und Polizeibehörden von Bund und Ländern seit Zuständigkeitswechsel, Bewertung der Neustrukturierung, Umsetzung des Geldwäschegesetzes, Verbesserung grenzüberschreitender Zusammenarbeit \r\n(insgesamt 26 Einzelfragen)"
  },
  "VORGANGSABLAUF": {
    "VORGANGSPOSITION": [
      {
        "ZUORDNUNG": "BT",
        "URHEBER": "Kleine Anfrage,  Urheber : Fraktion BÜNDNIS 90/DIE GRÜNEN ",
        "FUNDSTELLE": "02.05.2018 - BT-Drucksache 19/1959",
        "FUNDSTELLE_LINK": "http://dipbt.bundestag.de:80/dip21/btd/19/019/1901959.pdf",
        "PERSOENLICHER_URHEBER": [
          {
            "VORNAME": "Lisa",
            "NACHNAME": "Paus",
            "FUNKTION": "MdB",
            "FRAKTION": "BÜNDNIS 90/DIE GRÜNEN",
            "AKTIVITAETSART": "Kleine Anfrage"
          },
          {
            "VORNAME": "Irene",
            "NACHNAME": "Mihalic",
            "FUNKTION": "MdB",
            "FRAKTION": "BÜNDNIS 90/DIE GRÜNEN",
            "AKTIVITAETSART": "Kleine Anfrage"
          }
        ]
      },
      {
        "ZUORDNUNG": "BT",
        "URHEBER": "Antwort,  Urheber : Bundesregierung, Bundesministerium der Finanzen (federführend)",
        "FUNDSTELLE": "22.05.2018 - BT-Drucksache 19/2263",
        "FUNDSTELLE_LINK": "http://dipbt.bundestag.de:80/dip21/btd/19/022/1902263.pdf"
      }
    ]
  }
}
