{
  "vorgangId": "257095",
  "VORGANG": {
    "WAHLPERIODE": "19",
    "VORGANGSTYP": "Kleine Anfrage",
    "TITEL": "Wirksamkeit der Maßnahmen zur Korruptionsbekämpfung in der internationalen Zusammenarbeit",
    "INITIATIVE": "Fraktion BÜNDNIS 90/DIE GRÜNEN",
    "AKTUELLER_STAND": "Beantwortet",
    "SIGNATUR": "",
    "GESTA_ORDNUNGSNUMMER": "",
    "WICHTIGE_DRUCKSACHE": [
      {
        "DRS_HERAUSGEBER": "BT",
        "DRS_NUMMER": "19/16182",
        "DRS_TYP": "Kleine Anfrage",
        "DRS_LINK": "http://dipbt.bundestag.de:80/dip21/btd/19/161/1916182.pdf"
      },
      {
        "DRS_HERAUSGEBER": "BT",
        "DRS_NUMMER": "19/16972",
        "DRS_TYP": "Antwort",
        "DRS_LINK": "http://dipbt.bundestag.de:80/dip21/btd/19/169/1916972.pdf"
      }
    ],
    "EU_DOK_NR": "",
    "SACHGEBIET": "Entwicklungspolitik",
    "SCHLAGWORT": [
      "Bundesministerium für wirtschaftliche Zusammenarbeit und Entwicklung",
      "Bundesmittel",
      "Deutsches Evaluierungsinstitut der Entwicklungszusammenarbeit",
      "Drittstaat",
      {
        "_fundstelle": "true",
        "__cdata": "Entwicklungszusammenarbeit"
      },
      "Evaluation",
      {
        "_fundstelle": "true",
        "__cdata": "Korruption"
      },
      "Öffentlichkeitsarbeit der Bundesregierung",
      "Personalentwicklung",
      "Whistleblowing"
    ],
    "ABSTRAKT": "(insgesamt 27 Einzelfragen)"
  }
}
