{
  "vorgangId": "242617",
  "VORGANG": {
    "WAHLPERIODE": "19",
    "VORGANGSTYP": "Kleine Anfrage",
    "TITEL": "Reisemarkt in Deutschland",
    "INITIATIVE": "Fraktion der FDP",
    "AKTUELLER_STAND": "Beantwortet",
    "SIGNATUR": "",
    "GESTA_ORDNUNGSNUMMER": "",
    "WICHTIGE_DRUCKSACHE": [
      {
        "DRS_HERAUSGEBER": "BT",
        "DRS_NUMMER": "19/6534",
        "DRS_TYP": "Kleine Anfrage",
        "DRS_LINK": "http://dipbt.bundestag.de:80/dip21/btd/19/065/1906534.pdf"
      },
      {
        "DRS_HERAUSGEBER": "BT",
        "DRS_NUMMER": "19/7254",
        "DRS_TYP": "Antwort",
        "DRS_LINK": "http://dipbt.bundestag.de:80/dip21/btd/19/072/1907254.pdf"
      }
    ],
    "EU_DOK_NR": "",
    "SACHGEBIET": [
      "Wirtschaft",
      "Sport, Freizeit und Tourismus"
    ],
    "SCHLAGWORT": [
      "Berufsausbildung",
      "Elektronischer Handel",
      {
        "_fundstelle": "true",
        "__cdata": "Reiseunternehmen"
      },
      "Tourismus"
    ],
    "ABSTRAKT": "(insgesamt 26 Einzelfragen)"
  },
  "VORGANGSABLAUF": {
    "VORGANGSPOSITION": [
      {
        "ZUORDNUNG": "BT",
        "URHEBER": "Kleine Anfrage,  Urheber : Fraktion der FDP ",
        "FUNDSTELLE": "14.12.2018 - BT-Drucksache 19/6534",
        "FUNDSTELLE_LINK": "http://dipbt.bundestag.de:80/dip21/btd/19/065/1906534.pdf",
        "PERSOENLICHER_URHEBER": [
          {
            "PERSON_TITEL": "Dr. ",
            "VORNAME": "Marcel",
            "NACHNAME": "Klinge",
            "FUNKTION": "MdB",
            "FRAKTION": "FDP",
            "AKTIVITAETSART": "Kleine Anfrage"
          },
          {
            "VORNAME": "Michael",
            "NACHNAME": "Theurer",
            "FUNKTION": "MdB",
            "FRAKTION": "FDP",
            "AKTIVITAETSART": "Kleine Anfrage"
          }
        ]
      },
      {
        "ZUORDNUNG": "BT",
        "URHEBER": "Antwort,  Urheber : Bundesregierung, Bundesministerium für Wirtschaft und Energie (federführend)",
        "FUNDSTELLE": "21.01.2019 - BT-Drucksache 19/7254",
        "FUNDSTELLE_LINK": "http://dipbt.bundestag.de:80/dip21/btd/19/072/1907254.pdf"
      }
    ]
  }
}
