{
  "vorgangId": "244951",
  "VORGANG": {
    "WAHLPERIODE": "19",
    "VORGANGSTYP": "Kleine Anfrage",
    "TITEL": "Tornado-Nachfolge und Zukunftsfähigkeit der Luftwaffe",
    "INITIATIVE": "Fraktion der FDP",
    "AKTUELLER_STAND": "Beantwortet",
    "SIGNATUR": "",
    "GESTA_ORDNUNGSNUMMER": "",
    "WICHTIGE_DRUCKSACHE": [
      {
        "DRS_HERAUSGEBER": "BT",
        "DRS_NUMMER": "19/8311",
        "DRS_TYP": "Kleine Anfrage",
        "DRS_LINK": "http://dipbt.bundestag.de:80/dip21/btd/19/083/1908311.pdf"
      },
      {
        "DRS_HERAUSGEBER": "BT",
        "DRS_NUMMER": "19/9353",
        "DRS_TYP": "Antwort",
        "DRS_LINK": "http://dipbt.bundestag.de:80/dip21/btd/19/093/1909353.pdf"
      }
    ],
    "EU_DOK_NR": "",
    "SACHGEBIET": "Verteidigung",
    "SCHLAGWORT": [
      "Auslandseinsatz der Bundeswehr",
      "Bundeswehr",
      "Eurofighter",
      {
        "_fundstelle": "true",
        "__cdata": "Kampfflugzeug"
      },
      "Luftwaffe",
      "Militärbündnis",
      "Militärische Luftfahrt",
      "NATO",
      "Rüstungsindustrie",
      "Tornado (Kampfflugzeug)",
      "Verteidigungsausgaben"
    ],
    "ABSTRAKT": "(insgesamt 43 Einzelfragen)"
  },
  "VORGANGSABLAUF": {
    "VORGANGSPOSITION": [
      {
        "ZUORDNUNG": "BT",
        "URHEBER": "Kleine Anfrage,  Urheber : Fraktion der FDP ",
        "FUNDSTELLE": "13.03.2019 - BT-Drucksache 19/8311",
        "FUNDSTELLE_LINK": "http://dipbt.bundestag.de:80/dip21/btd/19/083/1908311.pdf",
        "PERSOENLICHER_URHEBER": [
          {
            "PERSON_TITEL": "Dr.",
            "VORNAME": "Marcus",
            "NACHNAME": "Faber",
            "FUNKTION": "MdB",
            "FRAKTION": "FDP",
            "AKTIVITAETSART": "Kleine Anfrage"
          },
          {
            "VORNAME": "Alexander",
            "NAMENSZUSATZ": "Graf",
            "NACHNAME": "Lambsdorff",
            "FUNKTION": "MdB",
            "FRAKTION": "FDP",
            "AKTIVITAETSART": "Kleine Anfrage"
          }
        ]
      },
      {
        "ZUORDNUNG": "BT",
        "URHEBER": "Antwort,  Urheber : Bundesregierung, Bundesministerium der Verteidigung (federführend)",
        "FUNDSTELLE": "09.04.2019 - BT-Drucksache 19/9353",
        "FUNDSTELLE_LINK": "http://dipbt.bundestag.de:80/dip21/btd/19/093/1909353.pdf"
      }
    ]
  }
}
