{
  "vorgangId": "84869",
  "VORGANG": {
    "WAHLPERIODE": "15",
    "VORGANGSTYP": "Fragestunde",
    "TITEL": "Unterzeichnung der Finanzierungsvereinbarung mit der Deutschen Bahn AG zum Weiterbau der Verkehrsprojekte Deutsche Einheit, Projekt 8.1 und 8.2 ICE-Trasse Nürnberg - Erfurt - Berlin (G-SIG: 15040063)",
    "AKTUELLER_STAND": "Beantwortet",
    "SIGNATUR": "",
    "GESTA_ORDNUNGSNUMMER": "",
    "PLENUM": {
      "PLPR_KLARTEXT": "Mündliche Antwort",
      "PLPR_HERAUSGEBER": "BT",
      "PLPR_NUMMER": "15/9",
      "PLPR_SEITEN": "498B - 500D",
      "PLPR_LINK": "http://dipbt.bundestag.de:80/dip21/btp/15/15009.pdf#P.498"
    },
    "EU_DOK_NR": "",
    "SCHLAGWORT": [
      "Berlin",
      "Eisenbahnstrecke",
      "Erfurt",
      "Intercity-Express",
      "Nürnberg",
      "Verkehrsfinanzierung",
      "Verkehrsprojekte Deutsche Einheit"
    ],
    "ABSTRAKT": ""
  },
  "VORGANGSABLAUF": {
    "VORGANGSPOSITION": [
      {
        "ZUORDNUNG": "BT",
        "URHEBER": "Mündliche Frage ",
        "FUNDSTELLE": "08.11.2002 - BT-Drucksache 15/42, Nr. 25, 26",
        "FUNDSTELLE_LINK": "http://dipbt.bundestag.de:80/dip21/btd/15/000/1500042.pdf"
      },
      {
        "ZUORDNUNG": "BT",
        "URHEBER": "Mündliche Antwort",
        "FUNDSTELLE": "13.11.2002 - BT-Plenarprotokoll 15/9, S. 498B - 500D",
        "FUNDSTELLE_LINK": "http://dipbt.bundestag.de:80/dip21/btp/15/15009.pdf#P.498",
        "PERSOENLICHER_URHEBER": [
          {
            "VORNAME": "Iris",
            "NACHNAME": "Gleicke",
            "FUNKTION": "Parl. Staatssekr.",
            "RESSORT": "Bundesministerium für Verkehr, Bau- und Wohnungswesen",
            "AKTIVITAETSART": "Antwort",
            "SEITE": "498B-500D"
          },
          {
            "VORNAME": "Manfred",
            "NACHNAME": "Grund",
            "FUNKTION": "MdB",
            "FRAKTION": "CDU/CSU",
            "AKTIVITAETSART": "Frage",
            "SEITE": "498B"
          },
          {
            "VORNAME": "Renate",
            "NACHNAME": "Blank",
            "FUNKTION": "MdB",
            "FRAKTION": "CDU/CSU",
            "AKTIVITAETSART": "Zusatzfrage",
            "SEITE": "498D,500B"
          },
          {
            "VORNAME": "Hartwig",
            "NACHNAME": "Fischer",
            "WAHLKREISZUSATZ": "Göttingen",
            "FUNKTION": "MdB",
            "FRAKTION": "CDU/CSU",
            "AKTIVITAETSART": "Zusatzfrage",
            "SEITE": "499B"
          },
          {
            "VORNAME": "Claudia",
            "NACHNAME": "Nolte",
            "FUNKTION": "MdB",
            "FRAKTION": "CDU/CSU",
            "AKTIVITAETSART": "Zusatzfrage",
            "SEITE": "499B,500C"
          }
        ]
      }
    ]
  }
}
