{
  "vorgangId": "228830",
  "VORGANG": {
    "WAHLPERIODE": "8",
    "VORGANGSTYP": "Fragestunde",
    "TITEL": "Linienführung der A 98 im Überlinger Raum sowie Einigung mit dem Land Baden-Württemberg über die \"seeferne Trasse\" (G-SIG: 00052540)",
    "AKTUELLER_STAND": "Beantwortet",
    "SIGNATUR": "",
    "GESTA_ORDNUNGSNUMMER": "",
    "PLENUM": {
      "PLPR_KLARTEXT": "Schriftliche Antwort",
      "PLPR_HERAUSGEBER": "BT",
      "PLPR_NUMMER": "08/190",
      "PLPR_SEITEN": "15003A - 15003B",
      "PLPR_LINK": "http://dipbt.bundestag.de:80/dip21/btp/08/08190.pdf#P.15003"
    },
    "EU_DOK_NR": "",
    "SCHLAGWORT": [
      "Autobahn",
      "Baden-Württemberg, Land",
      "Bodensee",
      "Überlingen, Stadt"
    ],
    "ABSTRAKT": ""
  },
  "VORGANGSABLAUF": {
    "VORGANGSPOSITION": [
      {
        "ZUORDNUNG": "BT",
        "URHEBER": "Mündliche Frage ",
        "FUNDSTELLE": "23.11.1979 - BT-Drucksache 08/3421, Nr. 77, 78",
        "FUNDSTELLE_LINK": "http://dipbt.bundestag.de:80/dip21/btd/08/034/0803421.pdf"
      },
      {
        "ZUORDNUNG": "BT",
        "URHEBER": "Schriftliche Antwort",
        "FUNDSTELLE": "30.11.1979 - BT-Plenarprotokoll 08/190, S. 15003A - 15003B",
        "FUNDSTELLE_LINK": "http://dipbt.bundestag.de:80/dip21/btp/08/08190.pdf#P.15003",
        "PERSOENLICHER_URHEBER": [
          {
            "VORNAME": "Lothar",
            "NACHNAME": "Wrede",
            "FUNKTION": "Parl. Staatssekr.",
            "RESSORT": "Bundesministerium für Verkehr",
            "AKTIVITAETSART": "Antwort",
            "SEITE": "15003A-B/Anl"
          },
          {
            "VORNAME": "Elmar",
            "NACHNAME": "Kolb",
            "FUNKTION": "MdB",
            "FRAKTION": "CDU/CSU",
            "AKTIVITAETSART": "Frage",
            "SEITE": "15003A"
          },
          {
            "VORNAME": "Elmar",
            "NACHNAME": "Kolb",
            "FUNKTION": "MdB",
            "FRAKTION": "CDU/CSU",
            "AKTIVITAETSART": "Frage",
            "SEITE": "15003A"
          }
        ]
      }
    ]
  }
}
