{
  "vorgangId": "86135",
  "VORGANG": {
    "WAHLPERIODE": "15",
    "VORGANGSTYP": "Bericht, Gutachten, Programm",
    "TITEL": "Bericht des Ausschusses für Bildung, Forschung und Technikfolgenabschätzung (17. Ausschuss) gemäß § 56a der Geschäftsordnung zur Technikfolgenabschätzung hier: Vorstudie \"Folgen von Umwelt- und Ressourcenschutz für Ausbildung, Qualifikation und Beschäftigung (G-SIG: 15000713)",
    "INITIATIVE": "Ausschuss für Bildung, Forschung und Technikfolgenabschätzung",
    "AKTUELLER_STAND": "Abgeschlossen - Ergebnis siehe Vorgangsablauf",
    "SIGNATUR": "",
    "GESTA_ORDNUNGSNUMMER": "",
    "WICHTIGE_DRUCKSACHE": {
      "DRS_HERAUSGEBER": "BT",
      "DRS_NUMMER": "14/9459",
      "DRS_TYP": "Bericht",
      "DRS_LINK": "http://dipbt.bundestag.de:80/dip21/btd/14/094/1409459.pdf"
    },
    "PLENUM": [
      {
        "PLPR_KLARTEXT": "Beratung",
        "PLPR_HERAUSGEBER": "BT",
        "PLPR_NUMMER": "15/79",
        "PLPR_SEITEN": "6948A - 6948B",
        "PLPR_LINK": "http://dipbt.bundestag.de:80/dip21/btp/15/15079.pdf#P.6948"
      },
      {
        "PLPR_KLARTEXT": "Mitteilung",
        "PLPR_HERAUSGEBER": "BT",
        "PLPR_NUMMER": "15/84",
        "PLPR_SEITEN": "7446C",
        "PLPR_LINK": "http://dipbt.bundestag.de:80/dip21/btp/15/15084.pdf#P.7446"
      }
    ],
    "EU_DOK_NR": "",
    "SACHGEBIET": [
      "Umwelt",
      "Arbeit und Beschäftigung",
      "Wissenschaft, Forschung und Technologie"
    ],
    "SCHLAGWORT": [
      "Arbeit",
      "Arbeitsplatz",
      "Berufsausbildung",
      "Beschäftigungspolitik",
      "Büro für Technikfolgen-Abschätzung beim Deutschen Bundestag",
      "Forschung und Technologie",
      "Geschäftsordnung des Deutschen Bundestages § 56a - Technikfolgenanalysen",
      "Technikfolgenabschätzung",
      "Umwelterziehung",
      "Umweltpolitik",
      "Umweltschutz"
    ],
    "ABSTRAKT": "Bericht des Büros für Technikfolgenabschätzung zum Forschungsstand: wirtschaftliche Bedeutung von Umweltinnovationen, Arbeitsplätze im und durch Umweltschutz, Nachhaltige Entwicklung und Arbeit, berufliche Qualifikation und Umweltbildung "
  },
  "VORGANGSABLAUF": {
    "VORGANGSPOSITION": [
      {
        "ZUORDNUNG": "BT",
        "URHEBER": "Unterrichtung,  Urheber : Ausschuss für Bildung, Forschung und Technikfolgenabschätzung ",
        "FUNDSTELLE": "13.06.2002 - BT-Drucksache 14/9459\nAnl. Verzeichnisse der Gutachten, Literatur und Tabellen",
        "FUNDSTELLE_LINK": "http://dipbt.bundestag.de:80/dip21/btd/14/094/1409459.pdf"
      },
      {
        "ZUORDNUNG": "BT",
        "URHEBER": "Beratung",
        "FUNDSTELLE": "27.11.2003 - BT-Plenarprotokoll 15/79, S. 6948A - 6948B",
        "FUNDSTELLE_LINK": "http://dipbt.bundestag.de:80/dip21/btp/15/15079.pdf#P.6948",
        "BESCHLUSS": {
          "BESCHLUSSSEITE": "6948B",
          "BESCHLUSSTENOR": "Überweisung"
        },
        "ZUWEISUNG": [
          {
            "AUSSCHUSS_KLARTEXT": "Ausschuss für Bildung, Forschung und Technikfolgenabschätzung",
            "FEDERFUEHRUNG": "federf&uuml;hrend"
          },
          {
            "AUSSCHUSS_KLARTEXT": "Ausschuss für Umwelt, Naturschutz und Reaktorsicherheit"
          },
          {
            "AUSSCHUSS_KLARTEXT": "Ausschuss für Verbraucherschutz, Ernährung und Landwirtschaft"
          },
          {
            "AUSSCHUSS_KLARTEXT": "Ausschuss für Wirtschaft und Arbeit"
          }
        ]
      },
      {
        "ZUORDNUNG": "BT",
        "URHEBER": "Mitteilung",
        "FUNDSTELLE": "19.12.2003 - BT-Plenarprotokoll 15/84, S. 7446C",
        "FUNDSTELLE_LINK": "http://dipbt.bundestag.de:80/dip21/btp/15/15084.pdf#P.7446",
        "VP_ABSTRAKT": "Mittlg: S.7446C - Mitteilung über Absehen von Berichterstattung"
      }
    ]
  }
}
