{
  "process": "18-68467",
  "VORGANG": {
    "WAHLPERIODE": "18",
    "VORGANGSTYP": "Kleine Anfrage",
    "TITEL": "Lieferungen deutscher Kleinwaffen und leichter Waffen an die Türkei",
    "INITIATIVE": "Fraktion DIE LINKE",
    "AKTUELLER_STAND": "Beantwortet",
    "SIGNATUR": "",
    "GESTA_ORDNUNGSNUMMER": "",
    "WICHTIGE_DRUCKSACHE": [
      {
        "DRS_HERAUSGEBER": "BT",
        "DRS_NUMMER": "18/5729",
        "DRS_TYP": "Kleine Anfrage",
        "DRS_LINK": "http://dipbt.bundestag.de:80/dip21/btd/18/057/1805729.pdf"
      },
      {
        "DRS_HERAUSGEBER": "BT",
        "DRS_NUMMER": "18/5939",
        "DRS_TYP": "Antwort",
        "DRS_LINK": "http://dipbt.bundestag.de:80/dip21/btd/18/059/1805939.pdf"
      }
    ],
    "EU_DOK_NR": "",
    "SACHGEBIET": [
      "Verteidigung",
      "Außenwirtschaft",
      "Außenpolitik und internationale Beziehungen"
    ],
    "SCHLAGWORT": [
      "Genehmigung",
      "Kleinwaffe",
      "Lizenz",
      "Opposition",
      "Rüstungsindustrie",
      "Syrien",
      "Türkei",
      "Waffenhandel"
    ],
    "ABSTRAKT": "Lieferungen an die Türkei sowie türkische Produktion in deutscher Lizenz, Reexporte bzw. Weitergaben, insbes. an bewaffnete syrische Oppositionsgruppen, beantragte und erteilte Genehmigungen, Einhaltung von Endverbleibserklärungen \n(insgesamt 20 Einzelfragen)"
  }
}
