{
  "vorgangId": "247979",
  "VORGANG": {
    "WAHLPERIODE": "19",
    "VORGANGSTYP": "Schriftliche Frage",
    "TITEL": "Besetzung der Leitung der Antidiskriminierungsstelle des Bundes",
    "AKTUELLER_STAND": "Beantwortet",
    "SIGNATUR": "",
    "GESTA_ORDNUNGSNUMMER": "",
    "WICHTIGE_DRUCKSACHE": {
      "DRS_HERAUSGEBER": "BT",
      "DRS_NUMMER": "19/8806",
      "DRS_TYP": "Schriftliche Fragen",
      "DRS_LINK": "http://dipbt.bundestag.de:80/dip21/btd/19/088/1908806.pdf"
    },
    "EU_DOK_NR": "",
    "SCHLAGWORT": [
      {
        "_fundstelle": "true",
        "__cdata": "Antidiskriminierungsstelle des Bundes"
      },
      "Bundesministerium f체r Familie, Senioren, Frauen und Jugend",
      "F체hrungskraft",
      "Personalbeschaffung"
    ],
    "ABSTRAKT": "Originaltext der Frage(n): \r\n \r\nWie ist der Stand des Verfahrens zur Besetzung der Leitung der Antidiskriminierungsstelle durch die Bundesministerin f체r Familie, Senioren, Frauen und Jugend, und wie ist der (ggbfs. vorl채ufige) Stand des verwaltungsgerichtlichen Verfahrens, dessentwegen der von der Bundesregierung beschlossene Vorschlag nach Angaben der Bundesregierung im November 2018 nicht umgesetzt werden konnte (s. Bundestagsdrucksache 19/5440, S. 64)? "
  }
}
