{
  "vorgangId": "243726",
  "VORGANG": {
    "WAHLPERIODE": "19",
    "VORGANGSTYP": "Schriftliche Frage",
    "TITEL": "CO2-Bepreisung im Rahmen des geplanten Klimaschutzgesetzes",
    "AKTUELLER_STAND": "Beantwortet",
    "SIGNATUR": "",
    "GESTA_ORDNUNGSNUMMER": "",
    "WICHTIGE_DRUCKSACHE": {
      "DRS_HERAUSGEBER": "BT",
      "DRS_NUMMER": "19/6961",
      "DRS_TYP": "Schriftliche Fragen",
      "DRS_LINK": "http://dipbt.bundestag.de:80/dip21/btd/19/069/1906961.pdf"
    },
    "EU_DOK_NR": "",
    "SCHLAGWORT": [
      "Emissionshandel",
      {
        "_fundstelle": "true",
        "__cdata": "Klimaschutz"
      },
      "Klimaschutzgesetz",
      {
        "_fundstelle": "true",
        "__cdata": "Kohlendioxid"
      },
      "Preis",
      "Treibhausgas",
      "Umweltabgabe"
    ],
    "ABSTRAKT": "Originaltext der Frage(n): \r\n \r\nIst davon auszugehen, dass das von der Bundesregierung angekündigte Klimaschutzgesetz eine nationale CO2-Bepreisung enthalten wird, nachdem der Regierungssprecher Steffen Seibert verkündet hat, eine CO2-Abgabe werde derzeit von der Bundesregierung geprüft (https://de.reuters. com/article/deutschland-klima-idDEKBN1OG16D), und falls die Verankerung einer nationalen CO2-Bepreisung nicht im geplanten Klimaschutzgesetz vorgesehen ist, bis wann kann davon ausgegangen werden, dass die Bundesregierung ihre Prüfungen beendet und ein Konzept für eine CO2-Bepreisung vorgelegt? "
  },
  "VORGANGSABLAUF": {
    "VORGANGSPOSITION": {
      "ZUORDNUNG": "BT",
      "URHEBER": "Schriftliche Frage/Schriftliche Antwort ",
      "FUNDSTELLE": "11.01.2019 - BT-Drucksache 19/6961, Nr. 126",
      "FUNDSTELLE_LINK": "http://dipbt.bundestag.de:80/dip21/btd/19/069/1906961.pdf",
      "PERSOENLICHER_URHEBER": [
        {
          "VORNAME": "Lisa",
          "NACHNAME": "Badum",
          "FUNKTION": "MdB",
          "FRAKTION": "BÜNDNIS 90/DIE GRÜNEN",
          "AKTIVITAETSART": "Frage"
        },
        {
          "VORNAME": "Rita",
          "NACHNAME": "Schwarzelühr-Sutter",
          "FUNKTION": "Parl. Staatssekr.",
          "RESSORT": "Bundesministerium für Umwelt, Naturschutz und nukleare Sicherheit",
          "AKTIVITAETSART": "Antwort"
        }
      ]
    }
  }
}
