{
  "vorgangId": "268506",
  "VORGANG": {
    "WAHLPERIODE": "19",
    "VORGANGSTYP": "Schriftliche Frage",
    "TITEL": "Tobruq-Legacy-Militärübungen in Litauen",
    "AKTUELLER_STAND": "Beantwortet",
    "SIGNATUR": "",
    "GESTA_ORDNUNGSNUMMER": "",
    "WICHTIGE_DRUCKSACHE": {
      "DRS_HERAUSGEBER": "BT",
      "DRS_NUMMER": "19/23238",
      "DRS_TYP": "Schriftliche Fragen",
      "DRS_LINK": "http://dipbt.bundestag.de:80/dip21/btd/19/232/1923238.pdf"
    },
    "EU_DOK_NR": "",
    "SCHLAGWORT": [
      {
        "_fundstelle": "true",
        "__cdata": "Litauen"
      },
      "Luftverteidigung",
      "Militärbündnis",
      {
        "_fundstelle": "true",
        "__cdata": "Militärische Übung"
      },
      "NATO-Truppen",
      "Russland",
      "Weißrussland"
    ],
    "ABSTRAKT": "Originaltext der Frage(n):\r\n  \r\nVerpflichtet der Umfang der Tobruq-Legacy-Militärübungen und &ndash; nach Kenntnis der Bundesregierung &ndash; der Umfang der Militärübungen \"Slawische Brüderschaft\" die teilnehmenden Länder dazu, die Nachbarländer, insbesondere Russland und Belarus, bzw. NATO-Mitglieder zu informieren und/oder Beobachter einzuladen, und falls ja, nach welchen Verträgen? \r\n"
  },
  "VORGANGSABLAUF": {
    "VORGANGSPOSITION": {
      "ZUORDNUNG": "BT",
      "URHEBER": "Schriftliche Frage/Schriftliche Antwort ",
      "FUNDSTELLE": "09.10.2020 - BT-Drucksache 19/23238, Nr. 93",
      "FUNDSTELLE_LINK": "http://dipbt.bundestag.de:80/dip21/btd/19/232/1923238.pdf",
      "PERSOENLICHER_URHEBER": [
        {
          "VORNAME": "Renata",
          "NACHNAME": "Alt",
          "FUNKTION": "MdB",
          "FRAKTION": "FDP",
          "AKTIVITAETSART": "Frage"
        },
        {
          "PERSON_TITEL": "Dr.",
          "VORNAME": "Peter",
          "NACHNAME": "Tauber",
          "FUNKTION": "Parl. Staatssekr.",
          "RESSORT": "Bundesministerium der Verteidigung",
          "AKTIVITAETSART": "Antwort"
        }
      ]
    }
  }
}
