{
  "vorgangId": "253577",
  "VORGANG": {
    "WAHLPERIODE": "19",
    "VORGANGSTYP": "Schriftliche Frage",
    "TITEL": "Mehrkosten für die Weiterführung der Siemensbahn nach Berlin-Spandau-Hakenfelde",
    "AKTUELLER_STAND": "Beantwortet",
    "SIGNATUR": "",
    "GESTA_ORDNUNGSNUMMER": "",
    "WICHTIGE_DRUCKSACHE": {
      "DRS_HERAUSGEBER": "BT",
      "DRS_NUMMER": "19/13020",
      "DRS_TYP": "Schriftliche Fragen",
      "DRS_LINK": "http://dipbt.bundestag.de:80/dip21/btd/19/130/1913020.pdf"
    },
    "EU_DOK_NR": "",
    "SCHLAGWORT": [
      "Bahnstrecke",
      "Berlin",
      "Deutsche Bahn",
      "Kosten",
      {
        "_fundstelle": "true",
        "__cdata": "S-Bahn"
      },
      "Schienenpersonenverkehr",
      {
        "_fundstelle": "true",
        "__cdata": "Siemens"
      },
      {
        "_fundstelle": "true",
        "__cdata": "Streckenbau"
      }
    ],
    "ABSTRAKT": "Originaltext der Frage(n): \r\n \r\nWelche Mehrkosten würden nach Kenntnis der Bundesregierung bzw. der DB AG durch die Weiterführung der Siemensbahn nach Berlin-Spandau-Hakenfelde entstehen, und wer würde dafür aufkommen?"
  }
}
