{
  "vorgangId": "243560",
  "VORGANG": {
    "WAHLPERIODE": "19",
    "VORGANGSTYP": "Schriftliche Frage",
    "TITEL": "Koordination der Seenotrettung durch die libysche Küstenwache",
    "AKTUELLER_STAND": "Beantwortet",
    "SIGNATUR": "",
    "GESTA_ORDNUNGSNUMMER": "",
    "WICHTIGE_DRUCKSACHE": {
      "DRS_HERAUSGEBER": "BT",
      "DRS_NUMMER": "19/6961",
      "DRS_TYP": "Schriftliche Fragen",
      "DRS_LINK": "http://dipbt.bundestag.de:80/dip21/btd/19/069/1906961.pdf"
    },
    "EU_DOK_NR": "",
    "SCHLAGWORT": [
      "Italien",
      "Küstenwache",
      {
        "_fundstelle": "true",
        "__cdata": "Libyen"
      },
      {
        "_fundstelle": "true",
        "__cdata": "Seenotrettung"
      }
    ],
    "ABSTRAKT": "Originaltext der Frage(n): \r\n \r\nWie schätzt die Bundesregierung die Fähigkeit der libyschen Leitstelle zur Seenotrettung, die seit Juni 2018 anstelle des italienischen Maritime Rescue Coordination Center (MRCC) für die Koordinierung von Einsätzen zwischen Libyen und Italien zuständig ist, zur see- und völkerrechtskonformen Koordination von Rettungseinsätzen ein, insbesondere hinsichtlich der Einhaltung des Non-refoulement-Gebots (www.zeit.de/ gesellschaft/zeitgeschehen/2018-07/seenotrettung- aquarius-fluechtlinge-mittelmeer-libyen-eu/ komplettansicht), und inwiefern befürwortet sie die Entscheidung der italienischen Regierung die Koordination der Seenotrettung an die libysche Küstenwache abzugeben? "
  },
  "VORGANGSABLAUF": {
    "VORGANGSPOSITION": {
      "ZUORDNUNG": "BT",
      "URHEBER": "Schriftliche Frage/Schriftliche Antwort ",
      "FUNDSTELLE": "11.01.2019 - BT-Drucksache 19/6961, Nr. 54",
      "FUNDSTELLE_LINK": "http://dipbt.bundestag.de:80/dip21/btd/19/069/1906961.pdf",
      "PERSOENLICHER_URHEBER": [
        {
          "VORNAME": "Luise",
          "NACHNAME": "Amtsberg",
          "FUNKTION": "MdB",
          "FRAKTION": "BÜNDNIS 90/DIE GRÜNEN",
          "AKTIVITAETSART": "Frage"
        },
        {
          "VORNAME": "Walter J.",
          "NACHNAME": "Lindner",
          "FUNKTION": "Staatssekr.",
          "RESSORT": "Auswärtiges Amt",
          "AKTIVITAETSART": "Antwort"
        }
      ]
    }
  }
}
