{
  "vorgangId": "35042",
  "VORGANG": {
    "WAHLPERIODE": "17",
    "VORGANGSTYP": "Über- und außerplanmäßige Haushaltsausgaben",
    "TITEL": "Haushaltsführung 2010\nÜber- und außerplanmäßige Ausgaben und Verpflichtungsermächtigungen im vierten Vierteljahr des Haushaltsjahres 2010",
    "INITIATIVE": "Bundesministerium der Finanzen",
    "AKTUELLER_STAND": "Abgeschlossen",
    "SIGNATUR": "",
    "GESTA_ORDNUNGSNUMMER": "",
    "WICHTIGE_DRUCKSACHE": [
      {
        "DRS_HERAUSGEBER": "BR",
        "DRS_NUMMER": "227/11",
        "DRS_TYP": "Unterrichtung",
        "DRS_LINK": "http://dipbt.bundestag.de:80/dip21/brd/2011/0227-11.pdf"
      },
      {
        "DRS_HERAUSGEBER": "BT",
        "DRS_NUMMER": "17/5647",
        "DRS_TYP": "Unterrichtung",
        "DRS_LINK": "http://dipbt.bundestag.de:80/dip21/btd/17/056/1705647.pdf"
      }
    ],
    "PLENUM": {
      "PLPR_KLARTEXT": "Mitteilung des federführenden Ausschusses",
      "PLPR_HERAUSGEBER": "BT",
      "PLPR_NUMMER": "17/189",
      "PLPR_SEITEN": "22859A - 22859C",
      "PLPR_LINK": "http://dipbt.bundestag.de:80/dip21/btp/17/17189.pdf#P.22859"
    },
    "EU_DOK_NR": "",
    "SACHGEBIET": "Öffentliche Finanzen, Steuern und Abgaben",
    "SCHLAGWORT": [
      "Über- und außerplanmäßige Haushaltsausgaben: Haushaltsjahr 2010",
      "Verpflichtungsermächtigung"
    ],
    "ABSTRAKT": ""
  },
  "VORGANGSABLAUF": {
    "VORGANGSPOSITION": [
      {
        "ZUORDNUNG": "BR",
        "URHEBER": "Unterrichtung,  Urheber : Bundesministerium der Finanzen ",
        "FUNDSTELLE": "13.04.2011 - BR-Drucksache 227/11",
        "FUNDSTELLE_LINK": "http://dipbt.bundestag.de:80/dip21/brd/2011/0227-11.pdf",
        "ZUWEISUNG": {
          "AUSSCHUSS_KLARTEXT": "Finanzausschuss",
          "FEDERFUEHRUNG": "federf&uuml;hrend"
        }
      },
      {
        "ZUORDNUNG": "BT",
        "URHEBER": "Unterrichtung,  Urheber : Bundesregierung, Bundesministerium der Finanzen (federführend)",
        "FUNDSTELLE": "14.04.2011 - BT-Drucksache 17/5647",
        "FUNDSTELLE_LINK": "http://dipbt.bundestag.de:80/dip21/btd/17/056/1705647.pdf"
      },
      {
        "ZUORDNUNG": "BT",
        "URHEBER": "Überweisung gemäß § 80 Abs. 3 Geschäftsordnung BT,  Urheber : Bundestag ",
        "FUNDSTELLE": "13.05.2011 - BT-Drucksache 17/5820",
        "FUNDSTELLE_LINK": "http://dipbt.bundestag.de:80/dip21/btd/17/058/1705820.pdf",
        "ZUWEISUNG": {
          "AUSSCHUSS_KLARTEXT": "Haushaltsausschuss",
          "FEDERFUEHRUNG": "federf&uuml;hrend"
        }
      },
      {
        "ZUORDNUNG": "BT",
        "URHEBER": "Mitteilung des federführenden Ausschusses",
        "FUNDSTELLE": "19.07.2012 - BT-Plenarprotokoll 17/189, S. 22859A - 22859C",
        "FUNDSTELLE_LINK": "http://dipbt.bundestag.de:80/dip21/btp/17/17189.pdf#P.22859",
        "VP_ABSTRAKT": "S. 22859A - Mitteilung über Absehen von Berichterstattung"
      }
    ]
  }
}
