{
  "process": "18-74002",
  "VORGANG": {
    "WAHLPERIODE": "18",
    "VORGANGSTYP": "EU-Vorlage",
    "TITEL": "Sonderbericht des Europäischen Rechnungshofs Nr. 24/2015\nBekämpfung des innergemeinschaftlichen MwSt.-Betrugs: Weitere Maßnahmen sind erforderlich \nRatsdok. 6918/16; ERH 24/2015",
    "INITIATIVE": "Bundestag",
    "AKTUELLER_STAND": "",
    "SIGNATUR": "",
    "GESTA_ORDNUNGSNUMMER": "",
    "WICHTIGE_DRUCKSACHE": {
      "DRS_HERAUSGEBER": "BT",
      "DRS_NUMMER": "18/8293",
      "DRS_TYP": "Unterrichtung",
      "DRS_LINK": "http://dipbt.bundestag.de:80/dip21/btd/18/082/1808293.pdf"
    },
    "PLENUM": {
      "PLPR_KLARTEXT": "Mitteilung des federführenden Ausschusses",
      "PLPR_HERAUSGEBER": "BT",
      "PLPR_NUMMER": "18/174",
      "PLPR_SEITEN": "17244D - 17245C",
      "PLPR_LINK": "http://dipbt.bundestag.de:80/dip21/btp/18/18174.pdf#P.17244"
    },
    "EU_DOK_NR": "Ratsdok. 6918/16",
    "ABSTRAKT": ""
  }
}
