{
  "vorgangId": "125040",
  "VORGANG": {
    "WAHLPERIODE": "13",
    "VORGANGSTYP": "Fragestunde",
    "TITEL": "Bundesministerien mit Mittelansätzen für Maßnahmen der auswärtigen Kulturpolitik (G-SIG: 13052739)",
    "AKTUELLER_STAND": "Beantwortet",
    "SIGNATUR": "",
    "GESTA_ORDNUNGSNUMMER": "",
    "WICHTIGE_DRUCKSACHE": {
      "DRS_HERAUSGEBER": "BT",
      "DRS_NUMMER": "13/2645",
      "DRS_TYP": "Schriftliche Fragen",
      "DRS_LINK": "http://dipbt.bundestag.de:80/dip21/btd/13/026/1302645.pdf"
    },
    "EU_DOK_NR": "",
    "SCHLAGWORT": [
      "Auswärtige Kulturpolitik",
      "Bundeshaushalt"
    ],
    "ABSTRAKT": ""
  },
  "VORGANGSABLAUF": {
    "VORGANGSPOSITION": {
      "ZUORDNUNG": "BT",
      "URHEBER": "Schriftliche Frage/Schriftliche Antwort ",
      "FUNDSTELLE": "13.10.1995 - BT-Drucksache 13/2645, Nr. 61",
      "FUNDSTELLE_LINK": "http://dipbt.bundestag.de:80/dip21/btd/13/026/1302645.pdf",
      "PERSOENLICHER_URHEBER": [
        {
          "VORNAME": "Irmgard",
          "NACHNAME": "Karwatzki",
          "FUNKTION": "Parl. Staatssekr.",
          "RESSORT": "Bundesministerium der Finanzen",
          "AKTIVITAETSART": "Antwort"
        },
        {
          "VORNAME": "Siegfried",
          "NACHNAME": "Vergin",
          "FUNKTION": "MdB",
          "FRAKTION": "SPD",
          "AKTIVITAETSART": "Frage"
        }
      ]
    }
  }
}
