{
  "vorgangId": "111314",
  "VORGANG": {
    "WAHLPERIODE": "14",
    "VORGANGSTYP": "Antrag",
    "TITEL": "Weißbuch der Kommission der Europäischen Gemeinschaften: Strategie für eine zukünftige Chemikalienpolitik (G-SIG: 14012564)",
    "INITIATIVE": "Fraktion der CDU/CSU",
    "AKTUELLER_STAND": "Abgelehnt",
    "SIGNATUR": "",
    "GESTA_ORDNUNGSNUMMER": "",
    "WICHTIGE_DRUCKSACHE": [
      {
        "DRS_HERAUSGEBER": "BT",
        "DRS_NUMMER": "14/8029",
        "DRS_TYP": "Antrag"
      },
      {
        "DRS_HERAUSGEBER": "BT",
        "DRS_NUMMER": "14/9516",
        "DRS_TYP": "Beschlussempfehlung"
      }
    ],
    "PLENUM": [
      {
        "PLPR_KLARTEXT": "Beratung",
        "PLPR_HERAUSGEBER": "BT",
        "PLPR_NUMMER": "14/218",
        "PLPR_SEITEN": "21685D - 21686A",
        "PLPR_LINK": "http://dipbt.bundestag.de:80/dip21/btp/14/14218.pdf#P.21685"
      },
      {
        "PLPR_KLARTEXT": "Beratung",
        "PLPR_HERAUSGEBER": "BT",
        "PLPR_NUMMER": "14/249",
        "PLPR_SEITEN": "25366C - 25366D",
        "PLPR_LINK": "http://dipbt.bundestag.de:80/dip21/btp/14/14249.pdf#P.25366"
      }
    ],
    "EU_DOK_NR": "",
    "SACHGEBIET": [
      "Umwelt",
      "Wirtschaft"
    ],
    "SCHLAGWORT": [
      "Chemikalie",
      "Chemische Industrie",
      "Gefährlicher Stoff",
      "Gewerbliche Wirtschaft",
      "Umweltschutz",
      "Weißbuch der Kommission der Europäischen Gemeinschaften"
    ],
    "ABSTRAKT": "Reform des Chemikalienrechts auf der Grundlage des Weißbuchs der Europäischen Kommission; Einführung eines Systems zur Registrierung, Bewertung und Zulassung von Chemikalien (REACH); Auswirkungen der vorgeschlagenen Reformen auf den Chemiestandort Deutschland, insbesondere auf kleine und mittlere Unternehmen; Notwendigkeit von Nachbesserungen bei den Zulassungsverfahren für Stoffe mit besonders gefährlichen Eigenschaften; Verbesserung der Innovations- und Wettbewerbsfähigkeit der deutschen und europäischen Industrie "
  },
  "VORGANGSABLAUF": {
    "VORGANGSPOSITION": [
      {
        "ZUORDNUNG": "BT",
        "URHEBER": "Antrag,  Urheber : Fraktion der CDU/CSU ",
        "FUNDSTELLE": "22.01.2002 - BT-Drucksache 14/8029",
        "PERSOENLICHER_URHEBER": [
          {
            "PERSON_TITEL": "Dr.",
            "VORNAME": "Christian",
            "NACHNAME": "Ruck",
            "FUNKTION": "MdB",
            "FRAKTION": "CDU/CSU",
            "AKTIVITAETSART": "Antrag"
          },
          {
            "PERSON_TITEL": "Dr.",
            "VORNAME": "Peter",
            "NACHNAME": "Paziorek",
            "FUNKTION": "MdB",
            "FRAKTION": "CDU/CSU",
            "AKTIVITAETSART": "Antrag"
          }
        ]
      },
      {
        "ZUORDNUNG": "BT",
        "URHEBER": "Beratung",
        "FUNDSTELLE": "21.02.2002 - BT-Plenarprotokoll 14/218, S. 21685D - 21686A",
        "FUNDSTELLE_LINK": "http://dipbt.bundestag.de:80/dip21/btp/14/14218.pdf#P.21685",
        "PERSOENLICHER_URHEBER": [
          {
            "PERSON_TITEL": "Dr.",
            "VORNAME": "Carola",
            "NACHNAME": "Reimann",
            "FUNKTION": "MdB",
            "FRAKTION": "SPD",
            "AKTIVITAETSART": "Rede (zu Protokoll gegeben)",
            "SEITE": "21697B-216998D/Anl"
          },
          {
            "PERSON_TITEL": "Dr.",
            "VORNAME": "Christian",
            "NACHNAME": "Ruck",
            "FUNKTION": "MdB",
            "FRAKTION": "CDU/CSU",
            "AKTIVITAETSART": "Rede (zu Protokoll gegeben)",
            "SEITE": "21698D-21700A/Anl"
          },
          {
            "VORNAME": "Winfried",
            "NACHNAME": "Hermann",
            "FUNKTION": "MdB",
            "FRAKTION": "BÜNDNIS 90/DIE GRÜNEN",
            "AKTIVITAETSART": "Rede (zu Protokoll gegeben)",
            "SEITE": "21700A-21701A/Anl"
          },
          {
            "VORNAME": "Birgit",
            "NACHNAME": "Homburger",
            "FUNKTION": "MdB",
            "FRAKTION": "FDP",
            "AKTIVITAETSART": "Rede (zu Protokoll gegeben)",
            "SEITE": "21701A-C/Anl"
          },
          {
            "VORNAME": "Eva",
            "NACHNAME": "Bulling-Schröter",
            "FUNKTION": "MdB",
            "FRAKTION": "PDS",
            "AKTIVITAETSART": "Rede (zu Protokoll gegeben)",
            "SEITE": "21701C-21702B/Anl"
          }
        ],
        "BESCHLUSS": {
          "BESCHLUSSSEITE": "21686A",
          "BESCHLUSSTENOR": "Überweisung"
        },
        "ZUWEISUNG": [
          {
            "AUSSCHUSS_KLARTEXT": "Ausschuss für Umwelt, Naturschutz und Reaktorsicherheit",
            "FEDERFUEHRUNG": "federf&uuml;hrend"
          },
          {
            "AUSSCHUSS_KLARTEXT": "Ausschuss für die Angelegenheiten der Europäischen Union"
          },
          {
            "AUSSCHUSS_KLARTEXT": "Ausschuss für Wirtschaft und Technologie"
          }
        ]
      },
      {
        "ZUORDNUNG": "BT",
        "URHEBER": "Beschlussempfehlung und Bericht,  Urheber : Ausschuss für Umwelt, Naturschutz und Reaktorsicherheit ",
        "FUNDSTELLE": "24.06.2002 - BT-Drucksache 14/9516",
        "PERSOENLICHER_URHEBER": [
          {
            "PERSON_TITEL": "Dr.",
            "VORNAME": "Carola",
            "NACHNAME": "Reimann",
            "FUNKTION": "MdB",
            "FRAKTION": "SPD",
            "AKTIVITAETSART": "Berichterstattung"
          },
          {
            "PERSON_TITEL": "Dr.",
            "VORNAME": "Christian",
            "NACHNAME": "Ruck",
            "FUNKTION": "MdB",
            "FRAKTION": "CDU/CSU",
            "AKTIVITAETSART": "Berichterstattung"
          }
        ]
      },
      {
        "ZUORDNUNG": "BT",
        "URHEBER": "Beratung",
        "FUNDSTELLE": "05.07.2002 - BT-Plenarprotokoll 14/249, S. 25366C - 25366D",
        "FUNDSTELLE_LINK": "http://dipbt.bundestag.de:80/dip21/btp/14/14249.pdf#P.25366",
        "PERSOENLICHER_URHEBER": [
          {
            "PERSON_TITEL": "Dr.",
            "VORNAME": "Carola",
            "NACHNAME": "Reimann",
            "FUNKTION": "MdB",
            "FRAKTION": "SPD",
            "AKTIVITAETSART": "Rede (zu Protokoll gegeben)",
            "SEITE": "25385B-25386A/Anl"
          },
          {
            "VORNAME": "Marie-Luise",
            "NACHNAME": "Dött",
            "FUNKTION": "MdB",
            "FRAKTION": "CDU/CSU",
            "AKTIVITAETSART": "Rede (zu Protokoll gegeben)",
            "SEITE": "25386B-25387B/Anl"
          },
          {
            "VORNAME": "Winfried",
            "NACHNAME": "Hermann",
            "FUNKTION": "MdB",
            "FRAKTION": "BÜNDNIS 90/DIE GRÜNEN",
            "AKTIVITAETSART": "Rede (zu Protokoll gegeben)",
            "SEITE": "25387B-25388C/Anl"
          },
          {
            "VORNAME": "Birgit",
            "NACHNAME": "Homburger",
            "FUNKTION": "MdB",
            "FRAKTION": "FDP",
            "AKTIVITAETSART": "Rede (zu Protokoll gegeben)",
            "SEITE": "25388C-25389B/Anl"
          },
          {
            "VORNAME": "Eva",
            "NACHNAME": "Bulling-Schröter",
            "FUNKTION": "MdB",
            "FRAKTION": "PDS",
            "AKTIVITAETSART": "Rede (zu Protokoll gegeben)",
            "SEITE": "25389B-C/Anl"
          }
        ],
        "BESCHLUSS": {
          "BESCHLUSSSEITE": "25366D",
          "BESCHLUSSTENOR": "Ablehnung Drs 14/8029"
        }
      }
    ]
  }
}
