{
  "vorgangId": "106282",
  "VORGANG": {
    "WAHLPERIODE": "14",
    "VORGANGSTYP": "Antrag",
    "TITEL": "Frauenspezifische Gesundheitsversorgung (G-SIG: 14011263)",
    "INITIATIVE": [
      "Fraktion BÜNDNIS 90/DIE GRÜNEN",
      "Fraktion der SPD"
    ],
    "AKTUELLER_STAND": "Angenommen",
    "SIGNATUR": "",
    "GESTA_ORDNUNGSNUMMER": "",
    "WICHTIGE_DRUCKSACHE": [
      {
        "DRS_HERAUSGEBER": "BT",
        "DRS_NUMMER": "14/3858",
        "DRS_TYP": "Antrag"
      },
      {
        "DRS_HERAUSGEBER": "BT",
        "DRS_NUMMER": "14/7889",
        "DRS_TYP": "Beschlussempfehlung"
      }
    ],
    "PLENUM": [
      {
        "PLPR_KLARTEXT": "Beratung",
        "PLPR_HERAUSGEBER": "BT",
        "PLPR_NUMMER": "14/129",
        "PLPR_SEITEN": "12439B - 12453C",
        "PLPR_LINK": "http://dipbt.bundestag.de:80/dip21/btp/14/14129.pdf#P.12439"
      },
      {
        "PLPR_KLARTEXT": "Beratung",
        "PLPR_HERAUSGEBER": "BT",
        "PLPR_NUMMER": "14/215",
        "PLPR_SEITEN": "21372A - 21379C",
        "PLPR_LINK": "http://dipbt.bundestag.de:80/dip21/btp/14/14215.pdf#P.21372"
      }
    ],
    "EU_DOK_NR": "",
    "SACHGEBIET": [
      "Gesundheit",
      "Gesellschaftspolitik, soziale Gruppen"
    ],
    "SCHLAGWORT": [
      "Bericht der Bundesregierung",
      "Frau",
      "Frauenarbeit",
      "Frauenheilkunde",
      "Gesundheit",
      "Gesundheitswesen"
    ],
    "ABSTRAKT": "Berücksichtigung der geschlechtsspezifischen Unterschiede (i.S. des Gender-Mainstreaming) in Forschung und Gesundheitsversorgung: Erforschung der Zusammenhänge zwischen Gesundheit/Krankheit und sozialer Lage/Lebensphasen bei Mädchen und Frauen, kontinuierliche Berichterstattung, Modellversuche eines Mammographie-Screenings, Untersuchung von Karriereverläufen von Frauen, Präventionsmaßnahmen gegen HIV/AIDS, Verbesserung der gesundheitlichen Situation von Migrantinnen, regionale Frauengesundheitszentren, gesundheitliche Versorgung von Frauen im Spannungsfeld zwischen Beruf und Familie "
  },
  "VORGANGSABLAUF": {
    "VORGANGSPOSITION": [
      {
        "ZUORDNUNG": "BT",
        "URHEBER": "Antrag,  Urheber : Fraktion BÜNDNIS 90/DIE GRÜNEN, Fraktion der SPD ",
        "FUNDSTELLE": "07.07.2000 - BT-Drucksache 14/3858",
        "PERSOENLICHER_URHEBER": [
          {
            "VORNAME": "Helga",
            "NACHNAME": "Kühn-Mengel",
            "FUNKTION": "MdB",
            "FRAKTION": "SPD",
            "AKTIVITAETSART": "Antrag"
          },
          {
            "VORNAME": "Anni",
            "NACHNAME": "Brandt-Elsweier",
            "FUNKTION": "MdB",
            "FRAKTION": "SPD",
            "AKTIVITAETSART": "Antrag"
          }
        ]
      },
      {
        "ZUORDNUNG": "BT",
        "URHEBER": "Beratung",
        "FUNDSTELLE": "08.11.2000 - BT-Plenarprotokoll 14/129, S. 12439B - 12453C",
        "FUNDSTELLE_LINK": "http://dipbt.bundestag.de:80/dip21/btp/14/14129.pdf#P.12439",
        "PERSOENLICHER_URHEBER": [
          {
            "VORNAME": "Helga",
            "NACHNAME": "Kühn-Mengel",
            "FUNKTION": "MdB",
            "FRAKTION": "SPD",
            "AKTIVITAETSART": "Rede",
            "SEITE": "12439C-12442A"
          },
          {
            "VORNAME": "Annette",
            "NACHNAME": "Widmann-Mauz",
            "FUNKTION": "MdB",
            "FRAKTION": "CDU/CSU",
            "AKTIVITAETSART": "Rede",
            "SEITE": "12442A-12444B,12447D-12448A"
          },
          {
            "VORNAME": "Monika",
            "NACHNAME": "Knoche",
            "FUNKTION": "MdB",
            "FRAKTION": "BÜNDNIS 90/DIE GRÜNEN",
            "AKTIVITAETSART": "Rede",
            "SEITE": "12444B-12445C"
          },
          {
            "VORNAME": "Detlef",
            "NACHNAME": "Parr",
            "FUNKTION": "MdB",
            "FRAKTION": "FDP",
            "AKTIVITAETSART": "Rede",
            "SEITE": "12445D-12447A"
          },
          {
            "VORNAME": "Christa",
            "NACHNAME": "Nickels",
            "FUNKTION": "MdB",
            "FRAKTION": "BÜNDNIS 90/DIE GRÜNEN",
            "AKTIVITAETSART": "Rede",
            "SEITE": "12447A-C"
          },
          {
            "VORNAME": "Petra",
            "NACHNAME": "Bläss",
            "FUNKTION": "MdB",
            "FRAKTION": "PDS",
            "AKTIVITAETSART": "Rede",
            "SEITE": "12448A-12449A"
          },
          {
            "VORNAME": "Anni",
            "NACHNAME": "Brandt-Elsweier",
            "FUNKTION": "MdB",
            "FRAKTION": "SPD",
            "AKTIVITAETSART": "Rede",
            "SEITE": "12449A-12450B"
          },
          {
            "VORNAME": "Beatrix",
            "NACHNAME": "Philipp",
            "FUNKTION": "MdB",
            "FRAKTION": "CDU/CSU",
            "AKTIVITAETSART": "Rede",
            "SEITE": "12450B-12452B"
          },
          {
            "VORNAME": "Irmingard",
            "NACHNAME": "Schewe-Gerigk",
            "FUNKTION": "MdB",
            "FRAKTION": "BÜNDNIS 90/DIE GRÜNEN",
            "AKTIVITAETSART": "Rede",
            "SEITE": "12452B-12453C"
          }
        ],
        "BESCHLUSS": {
          "BESCHLUSSSEITE": "12453C",
          "BESCHLUSSTENOR": "Überweisung"
        },
        "ZUWEISUNG": [
          {
            "AUSSCHUSS_KLARTEXT": "Ausschuss für Gesundheit",
            "FEDERFUEHRUNG": "federf&uuml;hrend"
          },
          {
            "AUSSCHUSS_KLARTEXT": "Ausschuss für Arbeit und Sozialordnung"
          },
          {
            "AUSSCHUSS_KLARTEXT": "Ausschuss für Bildung, Forschung und Technikfolgenabschätzung"
          },
          {
            "AUSSCHUSS_KLARTEXT": "Ausschuss für die Angelegenheiten der Europäischen Union"
          },
          {
            "AUSSCHUSS_KLARTEXT": "Ausschuss für Familie, Senioren, Frauen und Jugend"
          },
          {
            "AUSSCHUSS_KLARTEXT": "Haushaltsausschuss"
          },
          {
            "AUSSCHUSS_KLARTEXT": "Innenausschuss"
          }
        ]
      },
      {
        "ZUORDNUNG": "BT",
        "URHEBER": "Beschlussempfehlung und Bericht,  Urheber : Ausschuss für Gesundheit ",
        "FUNDSTELLE": "17.12.2001 - BT-Drucksache 14/7889",
        "PERSOENLICHER_URHEBER": {
          "VORNAME": "Helga",
          "NACHNAME": "Kühn-Mengel",
          "FUNKTION": "MdB",
          "FRAKTION": "SPD",
          "AKTIVITAETSART": "Berichterstattung"
        }
      },
      {
        "ZUORDNUNG": "BT",
        "URHEBER": "Beratung",
        "FUNDSTELLE": "31.01.2002 - BT-Plenarprotokoll 14/215, S. 21372A - 21379C",
        "FUNDSTELLE_LINK": "http://dipbt.bundestag.de:80/dip21/btp/14/14215.pdf#P.21372",
        "PERSOENLICHER_URHEBER": [
          {
            "VORNAME": "Helga",
            "NACHNAME": "Kühn-Mengel",
            "FUNKTION": "MdB",
            "FRAKTION": "SPD",
            "AKTIVITAETSART": "Rede",
            "SEITE": "21372B-21373C"
          },
          {
            "VORNAME": "Annette",
            "NACHNAME": "Widmann-Mauz",
            "FUNKTION": "MdB",
            "FRAKTION": "CDU/CSU",
            "AKTIVITAETSART": "Rede",
            "SEITE": "21373C-21375D"
          },
          {
            "VORNAME": "Monika",
            "NACHNAME": "Knoche",
            "FUNKTION": "MdB",
            "FRAKTION": "BÜNDNIS 90/DIE GRÜNEN",
            "AKTIVITAETSART": "Rede",
            "SEITE": "21375D-21376C"
          },
          {
            "VORNAME": "Ina",
            "NACHNAME": "Lenke",
            "FUNKTION": "MdB",
            "FRAKTION": "FDP",
            "AKTIVITAETSART": "Rede",
            "SEITE": "21376D-21377C"
          },
          {
            "VORNAME": "Petra",
            "NACHNAME": "Bläss",
            "FUNKTION": "MdB",
            "FRAKTION": "PDS",
            "AKTIVITAETSART": "Rede",
            "SEITE": "21377C-21378B"
          },
          {
            "VORNAME": "Marlene",
            "NACHNAME": "Rupprecht",
            "FUNKTION": "MdB",
            "FRAKTION": "SPD",
            "AKTIVITAETSART": "Rede",
            "SEITE": "21378B-21379B"
          },
          {
            "VORNAME": "Jürgen",
            "NACHNAME": "Koppelin",
            "FUNKTION": "MdB",
            "FRAKTION": "FDP",
            "AKTIVITAETSART": "Schriftliche Erklärung gem. § 31 Geschäftsordnung BT",
            "SEITE": "21423D/Anl"
          }
        ],
        "BESCHLUSS": {
          "BESCHLUSSSEITE": "21379B",
          "BESCHLUSSTENOR": "Annahme Drs 14/3858"
        }
      }
    ]
  }
}
