{
  "vorgangId": "230523",
  "VORGANG": {
    "WAHLPERIODE": "19",
    "VORGANGSTYP": "Entschließungsantrag BT",
    "TITEL": "Entschließungsantrag zum Antrag betr. Fortsetzung der Beteiligung bewaffneter deutscher Streitkräfte zur Ausbildungsunterstützung der Sicherheitskräfte der Regierung der Region Kurdistan-Irak und der irakischen Streitkräfte",
    "INITIATIVE": "Fraktion DIE LINKE",
    "AKTUELLER_STAND": "Abgelehnt",
    "SIGNATUR": "",
    "GESTA_ORDNUNGSNUMMER": "",
    "WICHTIGE_DRUCKSACHE": {
      "DRS_HERAUSGEBER": "BT",
      "DRS_NUMMER": "19/223",
      "DRS_TYP": "Entschließungsantrag",
      "DRS_LINK": "http://dipbt.bundestag.de:80/dip21/btd/19/002/1900223.pdf"
    },
    "PLENUM": {
      "PLPR_KLARTEXT": "Beratung",
      "PLPR_HERAUSGEBER": "BT",
      "PLPR_NUMMER": "19/4",
      "PLPR_SEITEN": "224C - 233D",
      "PLPR_LINK": "http://dipbt.bundestag.de:80/dip21/btp/19/19004.pdf#P.224"
    },
    "EU_DOK_NR": "",
    "SACHGEBIET": [
      "Verteidigung",
      "Außenpolitik und internationale Beziehungen"
    ],
    "SCHLAGWORT": [
      "Ausfuhrverbot",
      {
        "_fundstelle": "true",
        "__cdata": "Auslandseinsatz der Bundeswehr"
      },
      {
        "_fundstelle": "true",
        "__cdata": "Irak"
      },
      "Kurden",
      "Militärische Ausbildung",
      "Waffenhandel"
    ],
    "ABSTRAKT": "Beendigung der deutschen Beteiligung an der Ausbildungsmission, Verzicht auf Rüstungsexporte in den Nordirak"
  }
}
