{
  "vorgangId": "92011",
  "VORGANG": {
    "WAHLPERIODE": "15",
    "VORGANGSTYP": "Selbständiger Antrag von Ländern auf Entschließung",
    "TITEL": "Entschließung des Bundesrates für einen Verzicht auf die Führung und Kontrolle des handgeführten Rinder-Bestandsregisters (G-SIG: 15021428)",
    "INITIATIVE": "Bayern",
    "AKTUELLER_STAND": "Nicht abgeschlossen - Einzelheiten siehe Vorgangsablauf",
    "SIGNATUR": "",
    "GESTA_ORDNUNGSNUMMER": "",
    "WICHTIGE_DRUCKSACHE": {
      "DRS_HERAUSGEBER": "BR",
      "DRS_NUMMER": "871/03",
      "DRS_TYP": "Antrag",
      "DRS_LINK": "http://dipbt.bundestag.de:80/dip21/brd/2003/0871-03.pdf"
    },
    "PLENUM": {
      "PLPR_KLARTEXT": "BR-Sitzung",
      "PLPR_HERAUSGEBER": "BR",
      "PLPR_NUMMER": "795",
      "PLPR_SEITEN": "492A",
      "PLPR_LINK": "http://dipbt.bundestag.de:80/dip21/brp/795.pdf#P.492"
    },
    "EU_DOK_NR": "",
    "SCHLAGWORT": {
      "_fundstelle": "true",
      "__cdata": "Rinder-Bestandsregister"
    },
    "ABSTRAKT": "Anerkennung des vorhandenen \"digitalen\" Bestandsbuches als ausreichende Bestandsbuchführung "
  },
  "VORGANGSABLAUF": {
    "VORGANGSPOSITION": [
      {
        "ZUORDNUNG": "BR",
        "URHEBER": "Länderantrag,  Urheber : Bayern ",
        "FUNDSTELLE": "20.11.2003 - BR-Drucksache 871/03",
        "FUNDSTELLE_LINK": "http://dipbt.bundestag.de:80/dip21/brd/2003/0871-03.pdf",
        "ZUWEISUNG": [
          {
            "AUSSCHUSS_KLARTEXT": "Ausschuss für Fragen der Europäischen Union",
            "FEDERFUEHRUNG": "federf&uuml;hrend"
          },
          {
            "AUSSCHUSS_KLARTEXT": "Agrarausschuss"
          },
          {
            "AUSSCHUSS_KLARTEXT": "Gesundheitsausschuss"
          }
        ]
      },
      {
        "ZUORDNUNG": "BR",
        "URHEBER": "Empfehlungen der Ausschüsse,  Urheber : Agrarausschuss, Ausschuss für Fragen der Europäischen Union, Gesundheitsausschuss ",
        "FUNDSTELLE": "08.12.2003 - BR-Drucksache 871/1/03",
        "FUNDSTELLE_LINK": "http://dipbt.bundestag.de:80/dip21/brd/2003/0871-1-03.pdf",
        "VP_ABSTRAKT": "Ablehnung"
      },
      {
        "ZUORDNUNG": "BR",
        "URHEBER": "BR-Sitzung",
        "FUNDSTELLE": "19.12.2003 - BR-Plenarprotokoll 795, S. 492A",
        "FUNDSTELLE_LINK": "http://dipbt.bundestag.de:80/dip21/brp/795.pdf#P.492",
        "BESCHLUSS": {
          "BESCHLUSSSEITE": "492A",
          "BESCHLUSSTENOR": "Ablehnung"
        }
      },
      {
        "ZUORDNUNG": "BR",
        "URHEBER": "Beschlussdrucksache,  Urheber : Bundesrat ",
        "FUNDSTELLE": "19.12.2003 - BR-Drucksache 871/03(B)",
        "FUNDSTELLE_LINK": "http://dipbt.bundestag.de:80/dip21/brd/2003/0871-03B.pdf"
      }
    ]
  }
}
