{
  "vorgangId": "4584",
  "VORGANG": {
    "WAHLPERIODE": "16",
    "VORGANGSTYP": "Kleine Anfrage",
    "TITEL": "Verunreinigte Lebensmittelprodukte mit gentechnisch verändertem Reis (G-SIG: 16011101)",
    "INITIATIVE": "Fraktion BÜNDNIS 90/DIE GRÜNEN",
    "AKTUELLER_STAND": "Beantwortet",
    "SIGNATUR": "",
    "GESTA_ORDNUNGSNUMMER": "",
    "WICHTIGE_DRUCKSACHE": [
      {
        "DRS_HERAUSGEBER": "BT",
        "DRS_NUMMER": "16/2731",
        "DRS_TYP": "Kleine Anfrage",
        "DRS_LINK": "http://dipbt.bundestag.de:80/dip21/btd/16/027/1602731.pdf"
      },
      {
        "DRS_HERAUSGEBER": "BT",
        "DRS_NUMMER": "16/3118",
        "DRS_TYP": "Antwort",
        "DRS_LINK": "http://dipbt.bundestag.de:80/dip21/btd/16/031/1603118.pdf"
      }
    ],
    "EU_DOK_NR": "",
    "SACHGEBIET": "Landwirtschaft und Ernährung",
    "SCHLAGWORT": [
      "Agro-Gentechnik",
      "Bundesforschungsanstalt für Ernährung und Lebensmittel",
      "Bundesinstitut für Risikobewertung",
      "Freisetzung gentechnisch veränderter Organismen",
      "Lebensmittelzusatzstoff",
      "Lebens- und Futtermittelüberwachung",
      "Reis"
    ],
    "ABSTRAKT": "Kontrollverfahren betr. Einfuhr von nicht genehmigtem, gentechnisch verändertem Reis, Abstimmung mit den Bundesländern, Analyseverfahren und -häufigkeit, Rückrufverfahren, Bewertung durch das Bundesinstitut für Risikobewertung, EU-Zulassungsverfahren für Genreis, Präventionsmaßnahmen\n   "
  },
  "VORGANGSABLAUF": {
    "VORGANGSPOSITION": [
      {
        "ZUORDNUNG": "BT",
        "URHEBER": "Kleine Anfrage,  Urheber : Fraktion BÜNDNIS 90/DIE GRÜNEN ",
        "FUNDSTELLE": "22.09.2006 - BT-Drucksache 16/2731",
        "FUNDSTELLE_LINK": "http://dipbt.bundestag.de:80/dip21/btd/16/027/1602731.pdf",
        "PERSOENLICHER_URHEBER": [
          {
            "VORNAME": "Cornelia",
            "NACHNAME": "Behm",
            "FUNKTION": "MdB",
            "FRAKTION": "BÜNDNIS 90/DIE GRÜNEN",
            "AKTIVITAETSART": "Kleine Anfrage"
          },
          {
            "VORNAME": "Hans-Josef",
            "NACHNAME": "Fell",
            "FUNKTION": "MdB",
            "FRAKTION": "BÜNDNIS 90/DIE GRÜNEN",
            "AKTIVITAETSART": "Kleine Anfrage"
          },
          {
            "VORNAME": "Winfried",
            "NACHNAME": "Hermann",
            "FUNKTION": "MdB",
            "FRAKTION": "BÜNDNIS 90/DIE GRÜNEN",
            "AKTIVITAETSART": "Kleine Anfrage"
          },
          {
            "VORNAME": "Peter",
            "NACHNAME": "Hettlich",
            "FUNKTION": "MdB",
            "FRAKTION": "BÜNDNIS 90/DIE GRÜNEN",
            "AKTIVITAETSART": "Kleine Anfrage"
          },
          {
            "VORNAME": "Ulrike",
            "NACHNAME": "Höfken",
            "FUNKTION": "MdB",
            "FRAKTION": "BÜNDNIS 90/DIE GRÜNEN",
            "AKTIVITAETSART": "Kleine Anfrage"
          },
          {
            "PERSON_TITEL": "Dr.",
            "VORNAME": "Anton",
            "NACHNAME": "Hofreiter",
            "FUNKTION": "MdB",
            "FRAKTION": "BÜNDNIS 90/DIE GRÜNEN",
            "AKTIVITAETSART": "Kleine Anfrage"
          },
          {
            "VORNAME": "Bärbel",
            "NACHNAME": "Höhn",
            "FUNKTION": "MdB",
            "FRAKTION": "BÜNDNIS 90/DIE GRÜNEN",
            "AKTIVITAETSART": "Kleine Anfrage"
          },
          {
            "VORNAME": "Sylvia",
            "NACHNAME": "Kotting-Uhl",
            "FUNKTION": "MdB",
            "FRAKTION": "BÜNDNIS 90/DIE GRÜNEN",
            "AKTIVITAETSART": "Kleine Anfrage"
          },
          {
            "VORNAME": "Undine",
            "NACHNAME": "Kurth",
            "WAHLKREISZUSATZ": "Quedlinburg",
            "FUNKTION": "MdB",
            "FRAKTION": "BÜNDNIS 90/DIE GRÜNEN",
            "AKTIVITAETSART": "Kleine Anfrage"
          },
          {
            "PERSON_TITEL": "Dr.",
            "VORNAME": "Reinhard",
            "NACHNAME": "Loske",
            "FUNKTION": "MdB",
            "FRAKTION": "BÜNDNIS 90/DIE GRÜNEN",
            "AKTIVITAETSART": "Kleine Anfrage"
          }
        ]
      },
      {
        "ZUORDNUNG": "BT",
        "URHEBER": "Antwort,  Urheber : Bundesregierung, Bundesministerium für Ernährung, Landwirtschaft und Verbraucherschutz (federführend)",
        "FUNDSTELLE": "27.10.2006 - BT-Drucksache 16/3118",
        "FUNDSTELLE_LINK": "http://dipbt.bundestag.de:80/dip21/btd/16/031/1603118.pdf"
      }
    ]
  }
}
