{
  "vorgangId": "27190",
  "VORGANG": {
    "WAHLPERIODE": "17",
    "VORGANGSTYP": "Schriftliche Frage",
    "TITEL": "Ratifikation des Freihandelsabkommens zwischen der EU und Peru und Kolumbien sowie des Assoziierungsabkommens zwischen der EU und den Staaten Zentralamerikas durch den Deutschen Bundestag",
    "AKTUELLER_STAND": "Beantwortet",
    "SIGNATUR": "",
    "GESTA_ORDNUNGSNUMMER": "",
    "WICHTIGE_DRUCKSACHE": {
      "DRS_HERAUSGEBER": "BT",
      "DRS_NUMMER": "17/1879",
      "DRS_TYP": "Schriftliche Fragen",
      "DRS_LINK": "http://dipbt.bundestag.de:80/dip21/btd/17/018/1701879.pdf"
    },
    "EU_DOK_NR": "",
    "SCHLAGWORT": [
      "Assoziierung",
      "Außenbeziehungen der EU",
      "Europäische Union",
      "Freihandel",
      "Internationale Wirtschaftsbeziehungen",
      "Kolumbien",
      "Mittelamerika",
      "Peru"
    ],
    "ABSTRAKT": "Originaltext der Frage(n): \n \nHandelt es sich beim Freihandelsabkommen zwischen der EU und Peru und Kolumbien sowie beim Assoziierungsabkommen zwischen der EU und den Staaten Zentralamerikas um gemischte Abkommen, die vom Deutschen Bundestag ratifiziert werden müssen, und wenn ja, für wann sind diese Ratifikationsprozesse vorgesehen? \n \nWann werden dem Deutschen Bundestag die Texte des Freihandelsabkommens zwischen der EU und Peru und Kolumbien sowie des Assoziierungsabkommens zwischen der EU und den Staaten Zentralamerikas offiziell in ihrer endgültigen Fassung zugeleitet?"
  },
  "VORGANGSABLAUF": {
    "VORGANGSPOSITION": {
      "ZUORDNUNG": "BT",
      "URHEBER": "Schriftliche Frage/Schriftliche Antwort ",
      "FUNDSTELLE": "28.05.2010 - BT-Drucksache 17/1879, Nr. 15, 16",
      "FUNDSTELLE_LINK": "http://dipbt.bundestag.de:80/dip21/btd/17/018/1701879.pdf",
      "PERSOENLICHER_URHEBER": [
        {
          "PERSON_TITEL": "Dr.",
          "VORNAME": "Bernhard",
          "NACHNAME": "Heitzer",
          "FUNKTION": "Staatssekr.",
          "RESSORT": "Bundesministerium für Wirtschaft und Technologie",
          "AKTIVITAETSART": "Antwort"
        },
        {
          "VORNAME": "Thilo",
          "NACHNAME": "Hoppe",
          "FUNKTION": "MdB",
          "FRAKTION": "BÜNDNIS 90/DIE GRÜNEN",
          "AKTIVITAETSART": "Frage"
        }
      ]
    }
  }
}
