{
  "vorgangId": "22603",
  "VORGANG": {
    "WAHLPERIODE": "17",
    "VORGANGSTYP": "Schriftliche Frage",
    "TITEL": "Realisierung des Lückenschlusses der Bundesautobahn 44 zwischen Kassel und Eisenach\n",
    "AKTUELLER_STAND": "Beantwortet",
    "SIGNATUR": "",
    "GESTA_ORDNUNGSNUMMER": "",
    "WICHTIGE_DRUCKSACHE": {
      "DRS_HERAUSGEBER": "BT",
      "DRS_NUMMER": "17/160",
      "DRS_TYP": "Schriftliche Fragen",
      "DRS_LINK": "http://dipbt.bundestag.de:80/dip21/btd/17/001/1700160.pdf"
    },
    "EU_DOK_NR": "",
    "SCHLAGWORT": [
      "Autobahn",
      "Eisenach",
      "Kassel",
      "Regierungsprogramm",
      "Straßenbau",
      "Verkehrsinvestition",
      "Verkehrsprojekte Deutsche Einheit"
    ],
    "ABSTRAKT": " \n \n \n \n   \n \n  Normal\n  0\n  21\n  \n   \n   \n   \n   \n  \n  \n \n   \n \n  \n \n /* Style Definitions */\n table.MsoNormalTable\n\t{mso-style-name:\"Normale Tabelle\";\n\tmso-style-parent:\"\";\n\tfont-size:10.0pt;\"Times New Roman\";}\n \n  Originaltext der Frage(n): \n \n  Welche konkreten Schritte wird die Bundesregierung vor dem Hintergrund, dass ausweislich des Koalitionsvertrages zwischen CDU, CSU und FDP (siehe Seite 57), die Bundesregierung anstrebt, alle Verkehrsprojekte Deutsche Einheit der Straße bis 2010 fertigzustellen, einleiten, um den Lückenschluss der Bundesautobahn 44 zwischen Kassel und Eisenach bis Ende 2010 zu realisieren, und gibt es im Rahmen der Auftragsverwaltung seitens der hessischen Landesregierung einen Zeit- und Projektplan für Planungen und Bau der Bundesautobahn 44, der den Zusagen der Bundesregierung angemessen Rechnung trägt?   \n \n \n "
  },
  "VORGANGSABLAUF": {
    "VORGANGSPOSITION": {
      "ZUORDNUNG": "BT",
      "URHEBER": "Schriftliche Frage/Schriftliche Antwort ",
      "FUNDSTELLE": "04.12.2009 - BT-Drucksache 17/160, Nr. 96",
      "FUNDSTELLE_LINK": "http://dipbt.bundestag.de:80/dip21/btd/17/001/1700160.pdf",
      "PERSOENLICHER_URHEBER": [
        {
          "VORNAME": "Jan",
          "NACHNAME": "Mücke",
          "FUNKTION": "Parl. Staatssekr.",
          "RESSORT": "Bundesministerium für Verkehr, Bau und Stadtentwicklung",
          "AKTIVITAETSART": "Antwort"
        },
        {
          "VORNAME": "Michael",
          "NACHNAME": "Roth",
          "WAHLKREISZUSATZ": "Heringen",
          "FUNKTION": "MdB",
          "FRAKTION": "SPD",
          "AKTIVITAETSART": "Frage"
        }
      ]
    }
  }
}
