{
  "vorgangId": "39142",
  "VORGANG": {
    "WAHLPERIODE": "17",
    "VORGANGSTYP": "Schriftliche Frage",
    "TITEL": "Sicherheitsanforderungen für die Endlagerung spezifischer radioaktiver Abfälle",
    "AKTUELLER_STAND": "Beantwortet",
    "SIGNATUR": "",
    "GESTA_ORDNUNGSNUMMER": "",
    "WICHTIGE_DRUCKSACHE": {
      "DRS_HERAUSGEBER": "BT",
      "DRS_NUMMER": "17/7279",
      "DRS_TYP": "Schriftliche Fragen",
      "DRS_LINK": "http://dipbt.bundestag.de:80/dip21/btd/17/072/1707279.pdf"
    },
    "EU_DOK_NR": "",
    "SCHLAGWORT": [
      "Bundesministerium für Umwelt, Naturschutz und Reaktorsicherheit",
      {
        "_fundstelle": "true",
        "__cdata": "Endlagerung radioaktiver Abfälle"
      },
      "Salzgitter",
      "Schacht Konrad"
    ],
    "ABSTRAKT": "Originaltext der Frage(n): \r\n \r\nWelche Sicherheitsanforderungen gelten für die Endlagerung der radioaktiven Abfälle, die auf den Bundestagsdrucksachen 17/6817, Antwort zu Frage 20 und 17/6954, Antwort zu Frage 203 erwähnt werden und weder Konradgängig noch hochradioaktiv wärmeentwickelnd sind, und welches Vorgehen inklusive Zeitplan hat das BMU gegebenenfalls für die Erarbeitung und Festlegung derartiger Sicherheitsanforderungen vorgesehen (bitte mit Angabe aller Meilensteine, Teilprojekte etc. sowie diesbezüglicher Aufträge an die Gesellschaft für Anlagen- und Reaktorsicherheit und andere)?"
  },
  "VORGANGSABLAUF": {
    "VORGANGSPOSITION": {
      "ZUORDNUNG": "BT",
      "URHEBER": "Schriftliche Frage/Schriftliche Antwort ",
      "FUNDSTELLE": "07.10.2011 - BT-Drucksache 17/7279, Nr. 89",
      "FUNDSTELLE_LINK": "http://dipbt.bundestag.de:80/dip21/btd/17/072/1707279.pdf",
      "PERSOENLICHER_URHEBER": [
        {
          "VORNAME": "Ursula",
          "NACHNAME": "Heinen-Esser",
          "FUNKTION": "Parl. Staatssekr.",
          "RESSORT": "Bundesministerium für Umwelt, Naturschutz und Reaktorsicherheit",
          "AKTIVITAETSART": "Antwort"
        },
        {
          "VORNAME": "Sylvia",
          "NACHNAME": "Kotting-Uhl",
          "FUNKTION": "MdB",
          "FRAKTION": "BÜNDNIS 90/DIE GRÜNEN",
          "AKTIVITAETSART": "Frage"
        }
      ]
    }
  }
}
