{
  "process": "17-55767",
  "VORGANG": {
    "WAHLPERIODE": "17",
    "VORGANGSTYP": "Schriftliche Frage",
    "TITEL": "Zwangsunterbringung von Straftätern nach Verbüßung der Strafe in der Forensischen Psychiatrie",
    "AKTUELLER_STAND": "Beantwortet",
    "SIGNATUR": "",
    "GESTA_ORDNUNGSNUMMER": "",
    "WICHTIGE_DRUCKSACHE": {
      "DRS_HERAUSGEBER": "BT",
      "DRS_NUMMER": "17/14712",
      "DRS_TYP": "Schriftliche Fragen",
      "DRS_LINK": "http://dipbt.bundestag.de:80/dip21/btd/17/147/1714712.pdf"
    },
    "EU_DOK_NR": "",
    "SCHLAGWORT": [
      "Gesetzgebung",
      "Maßregeln der Besserung und Sicherung",
      "Maßregelvollzug",
      "Psychiatrische Einrichtung",
      "Strafgefangener",
      "Strafvollzug",
      "Unterbringung"
    ],
    "ABSTRAKT": "Originaltext der Frage(n): \n \nIst es richtig, dass die zwangsweise Unterbringung von Straftätern nach Verbüßung der Strafe in der Forensik eine durchschnittliche Verweildauer von ca. vier bis sechs Jahren nach sich zieht, während nach dem Gesetz für psychisch Kranke (PsychKG) Zwangseingewiesene durchschnittlich etwa einen Monat in der Psychiatrie bleiben, und wie ist dieser sehr große Unterschied angesichts wahrscheinlich ähnlicher Fremdgefährdungsprognosen zu rechtfertigen?"
  }
}
